fluiddevops/__init__.py
fluiddevops/icat.py
fluiddevops/logger.py
fluiddevops/util.py
fluiddevops/mirror/__init__.py
fluiddevops/mirror/config.py
fluiddevops/mirror/vcs.py
fluiddevops/test/__init__.py
fluiddevops/test/test_icat.py
fluiddevops/test/test_mirror.py
fluiddevops/vendor/__init__.py
fluiddevops/vendor/bitbucket_cli/__init__.py
fluiddevops/vendor/bitbucket_cli/cli.py
fluiddevops/vendor/bitbucket_cli/config.py
fluiddevops/vendor/bitbucket_cli/repositories.py
fluiddevops/vendor/bitbucket_cli/scm.py
fluiddevops-0.0.4b0.dist-info/METADATA
fluiddevops-0.0.4b0.dist-info/RECORD
fluiddevops-0.0.4b0.dist-info/WHEEL
fluiddevops-0.0.4b0.dist-info/entry_points.txt
fluiddevops-0.0.4b0.dist-info/top_level.txt
