Metadata-Version: 2.1
Name: fluiddevops
Version: 0.0.4b0
Summary: Console scripts to make DevOps easier
Home-page: http://bitbucket.org/fluiddyn/fluiddevops
Author: FluidDyn Developers
Author-email: fluiddyn@freelists.org
License: CeCILL-B License
Keywords: DevOps,continuous integration,testing
Platform: UNKNOWN
Classifier: Development Status :: 4 - Beta
Classifier: Intended Audience :: Science/Research
Classifier: Intended Audience :: Education
Classifier: Topic :: Scientific/Engineering
Classifier: License :: OSI Approved :: BSD License
Classifier: Programming Language :: Python :: 2.7
Classifier: Programming Language :: Python :: 3
Requires-Python: >=2.7
Provides-Extra: doc
Provides-Extra: hg
Requires-Dist: requests (>=2.20.0)
Requires-Dist: future; python_version < "3"
Requires-Dist: futures; python_version < "3"
Requires-Dist: pathlib2; python_version < "3.4"
Requires-Dist: configparser; python_version < "3.5"
Requires-Dist: scandir; python_version < "3.5"
Provides-Extra: doc
Requires-Dist: sphinx; extra == 'doc'
Requires-Dist: sphinx-rtd-theme; extra == 'doc'
Requires-Dist: numpydoc; extra == 'doc'
Provides-Extra: hg
Requires-Dist: mercurial (==4.7.2); extra == 'hg'
Requires-Dist: hg-git (==0.8.12); extra == 'hg'
Requires-Dist: dulwich (==0.19.6); extra == 'hg'
Requires-Dist: hg-evolve (==8.3.1); extra == 'hg'
